axeh/__init__.py
axeh/cli.py
axeh/gitignore_api.py
axeh-0.1.3.dist-info/METADATA
axeh-0.1.3.dist-info/WHEEL
axeh-0.1.3.dist-info/entry_points.txt
axeh-0.1.3.dist-info/RECORD
